pyRawTools/__init__.py
pyRawTools/loader.py
pyRawTools/module/RawTools/CLParserForNetFramework.dll
pyRawTools/module/RawTools/CLParserForNetFramework.pdb
pyRawTools/module/RawTools/CheckBoxComboBox.dll
pyRawTools/module/RawTools/CheckBoxComboBox.pdb
pyRawTools/module/RawTools/LICENSE
pyRawTools/module/RawTools/Microsoft.Win32.Primitives.dll
pyRawTools/module/RawTools/NOTICE
pyRawTools/module/RawTools/OpenMcdf.Extensions.dll
pyRawTools/module/RawTools/OpenMcdf.dll
pyRawTools/module/RawTools/OxyPlot.WindowsForms.dll
pyRawTools/module/RawTools/OxyPlot.dll
pyRawTools/module/RawTools/RawFileReaderLicense
pyRawTools/module/RawTools/RawTools.exe
pyRawTools/module/RawTools/RawTools.exe.config
pyRawTools/module/RawTools/RawTools.pdb
pyRawTools/module/RawTools/RawToolsGUI.exe
pyRawTools/module/RawTools/RawToolsGUI.exe.config
pyRawTools/module/RawTools/RawToolsGUI.pdb
pyRawTools/module/RawTools/RawToolsViz.exe
pyRawTools/module/RawTools/RawToolsViz.exe.config
pyRawTools/module/RawTools/RawToolsViz.pdb
pyRawTools/module/RawTools/Serilog.Sinks.File.dll
pyRawTools/module/RawTools/Serilog.Sinks.File.pdb
pyRawTools/module/RawTools/Serilog.dll
pyRawTools/module/RawTools/SerilogLicense
pyRawTools/module/RawTools/System.AppContext.dll
pyRawTools/module/RawTools/System.Collections.Concurrent.dll
pyRawTools/module/RawTools/System.Collections.NonGeneric.dll
pyRawTools/module/RawTools/System.Collections.Specialized.dll
pyRawTools/module/RawTools/System.Collections.dll
pyRawTools/module/RawTools/System.ComponentModel.EventBasedAsync.dll
pyRawTools/module/RawTools/System.ComponentModel.Primitives.dll
pyRawTools/module/RawTools/System.ComponentModel.TypeConverter.dll
pyRawTools/module/RawTools/System.ComponentModel.dll
pyRawTools/module/RawTools/System.Console.dll
pyRawTools/module/RawTools/System.Data.Common.dll
pyRawTools/module/RawTools/System.Diagnostics.Contracts.dll
pyRawTools/module/RawTools/System.Diagnostics.Debug.dll
pyRawTools-0.2.3.dist-info/LICENSE
pyRawTools-0.2.3.dist-info/METADATA
pyRawTools-0.2.3.dist-info/WHEEL
pyRawTools-0.2.3.dist-info/top_level.txt
pyRawTools-0.2.3.dist-info/RECORD
