Metadata-Version: 2.1
Name: pyRawTools
Version: 0.2.3
Summary: pyRawTools is a Python package for loading Thermo MS data.
Home-page: https://github.com/EstrellaXD/pyRawTools
Author: EstrellaXD
Author-email: Estrella Pan <estrellaxd05@gmail.com>
Project-URL: Homepage, https://github.com/EstrellaXD/pyRawTools
Project-URL: Bug Tracker, https://github.com/EstrellaXD/pyRawTools/issues
Keywords: RAW MS data
Classifier: Programming Language :: Python :: 3
Classifier: License :: OSI Approved :: MIT License
Classifier: Operating System :: OS Independent
Requires-Python: >=3.8
License-File: LICENSE
Requires-Dist: pandas
